LICENSE.txt
MANIFEST.in
README.md
requirements.txt
setup.cfg
setup.py
prototwin_gymnasium/__init__.py
prototwin_gymnasium/env.py
prototwin_gymnasium.egg-info/PKG-INFO
prototwin_gymnasium.egg-info/SOURCES.txt
prototwin_gymnasium.egg-info/dependency_links.txt
prototwin_gymnasium.egg-info/requires.txt
prototwin_gymnasium.egg-info/top_level.txt