Metadata-Version: 2.4
Name: prototwin_gymnasium
Version: 0.2.0
Summary: The official base Gymnasium environment for ProtoTwin Connect.
Home-page: https://prototwin.com
Author: ProtoTwin
License: MIT
Keywords: Industrial Simulation,Simulation,Physics,Machine Learning,Reinforcement Learning,Robotics,Gymnasium
Classifier: Development Status :: 4 - Beta
Classifier: Intended Audience :: Developers
Classifier: Topic :: Scientific/Engineering :: Artificial Intelligence
Classifier: License :: OSI Approved :: MIT License
Classifier: Programming Language :: Python :: 3
License-File: LICENSE.txt
Requires-Dist: gymnasium
Requires-Dist: prototwin
Requires-Dist: asyncio
Requires-Dist: nest_asyncio
Requires-Dist: numpy
Requires-Dist: stable_baselines3
Dynamic: author
Dynamic: classifier
Dynamic: description
Dynamic: description-content-type
Dynamic: home-page
Dynamic: keywords
Dynamic: license
Dynamic: license-file
Dynamic: requires-dist
Dynamic: summary
